[
  {
    "cluster_id": "c-normal",
    "rules": [
      {
        "name": "c-normal-transfer",
        "rule": "{code} == '02'",
        "calculation": [
          {
            "key": "Fee Issuer",
            "exp": "{amount} * 0.01"
          },
          {
            "key": "Fee Acquirer",
            "exp": "{amount} * 0.02"
          },
          {
            "key": "Fee Destination",
            "exp": "{amount} * 0.04"
          }
        ]
      },
      {
        "name": "c-normal-withdrawal",
        "rule": "{code} == '01'",
        "calculation": [
          {
            "key": "Fee Issuer",
            "exp": "{amount} * 0.01"
          },
          {
            "key": "Fee Acquirer",
            "exp": "{amount} * 0.02"
          },
          {
            "key": "Fee Destination",
            "exp": "{amount} * 0.04"
          }
        ]
      }
    ]
  },
  {
    "cluster_id": "c-normal-prio",
    "rules": [
      {
        "name": "c-normal-prio-transfer",
        "rule": "{code} == '02'",
        "calculation": [
          {
            "key": "Fee Issuer",
            "exp": "{amount} * 0.01"
          },
          {
            "key": "Fee Acquirer",
            "exp": "{amount} * 0.02"
          },
          {
            "key": "Fee Destination",
            "exp": "{amount} * 0.04"
          }
        ]
      },
      {
        "name": "c-normal-prio-withdrawal",
        "rule": "{code} == '01'",
        "calculation": [
          {
            "key": "Fee Issuer",
            "exp": "{amount} * 0.01"
          },
          {
            "key": "Fee Acquirer",
            "exp": "{amount} * 0.02"
          },
          {
            "key": "Fee Destination",
            "exp": "{amount} * 0.04"
          }
        ]
      }
    ]
  },
  {
    "cluster_id": "default",
    "rules": [
      {
        "name": "all trx",
        "rule": null,
        "calculation": [
          {
            "key": "Fee Issuer",
            "exp": "0.0"
          },
          {
            "key": "Fee Acquirer",
            "exp": "0.0"
          },
          {
            "key": "Fee Destination",
            "exp": "0.0"
          }
        ]
      }
    ]
  }
]